heimdallr/__init__.py
heimdallr/all.py
heimdallr/base.py
heimdallr/network.py
heimdallr/instrument_control/__init__.py
heimdallr/instrument_control/instrument_control.py
heimdallr/instrument_control/categories/__init__.py
heimdallr/instrument_control/categories/all_ctgs.py
heimdallr/instrument_control/categories/oscilloscope_ctg.py
heimdallr/instrument_control/categories/rf_power_sensor_ctg.py
heimdallr/instrument_control/categories/rf_signal_generator_ctg.py
heimdallr/instrument_control/categories/spectrum_analyzer_ctg.py
heimdallr/instrument_control/categories/temperature_controller_ctg.py
heimdallr/instrument_control/categories/vector_network_analyzer_ctg.py
heimdallr/instrument_control/drivers/Agilent_E4400_dvr.py
heimdallr/instrument_control/drivers/Keysight_8360L_dvr.py
heimdallr/instrument_control/drivers/LakeShore_Model335_dvr.py
heimdallr/instrument_control/drivers/PNA_dvr.py
heimdallr/instrument_control/drivers/Rigol_DS1000Z_dvr.py
heimdallr/instrument_control/drivers/RohdeSchwarz_FSQ_dvr.py
heimdallr/instrument_control/drivers/RohdeSchwarz_NRP_dvr.py
heimdallr/instrument_control/drivers/RohdeSchwarz_NRX_dvr.py
heimdallr/instrument_control/drivers/Siglent_SSA3000X_dvr.py
heimdallr/instrument_control/drivers/__init__.py
heimdallr/instrument_control/drivers/all_drivers.py
heimdallr/ui/__init__.py
heimdallr/ui/ui.py
heimdallr/ui/widgets/__init__.py
heimdallr/ui/widgets/vector_network_analuzer_gui.py
heimdallr_py-0.0.0.dev1.dist-info/LICENSE
heimdallr_py-0.0.0.dev1.dist-info/METADATA
heimdallr_py-0.0.0.dev1.dist-info/WHEEL
heimdallr_py-0.0.0.dev1.dist-info/top_level.txt
heimdallr_py-0.0.0.dev1.dist-info/RECORD
