Metadata-Version: 2.1
Name: heimdallr-py
Version: 0.0.0.dev1
Summary: Modular instrument control and lab access via Python
Author-email: Grant Giesbrecht <grant.giesbrecht@colorado.edu>
Project-URL: Homepage, https://github.com/Grant-Giesbrecht/heimdallr
Project-URL: Issues, https://github.com/Grant-Giesbrecht/heimdallr/issues
Classifier: Programming Language :: Python :: 3
Classifier: License :: OSI Approved :: BSD License
Classifier: Operating System :: OS Independent
Requires-Python: >=3.8
License-File: LICENSE
Requires-Dist: numpy >=1.0.0
Requires-Dist: pyvisa >=1.0.0
Requires-Dist: pylogfile >=0.1.0
Requires-Dist: h5py >=3.0.0
Requires-Dist: colorama >=0.4.0
